{
  "meta": {
    "build": {
      "build-date": "2022-02-08",
      "codified-date": "2021-06-29",
      "platform": {
        "reproducible": "false",
        "version": "2.6.0"
      },
      "publication": "publication/2022-02-08-01",
      "repositories": [
        {
          "commit": "c4b9016a132dca38e2735e092d000701ab070e6c",
          "name": "sanipueblo/law-xml"
        },
        {
          "commit": "62eb65b1d4726b90dc52070b3463331cf2d9d6b6",
          "name": "sanipueblo/law-xml-codified"
        }
      ]
    },
    "canonical-urls": {
      "html": "https://law.sanipueblo.org",
      "html-bulk": "https://github.com/oll-test-repos/sanipueblo-law-html",
      "law-git": "https://github.com/oll-test-repos/sanipueblo-law",
      "static-assets": "https://github.com/sanipueblo/law-static-assets",
      "xml-bulk": "https://github.com/oll-test-repos/sanipueblo-law-xml"
    },
    "contact": {
      "email": "help@openlawlib.org"
    },
    "description": "",
    "history-start": "2017-04-19"
  }
}